my_mcp_project_mysql_last_push/__init__.py
my_mcp_project_mysql_last_push-0.1.4.dist-info/WHEEL
my_mcp_project_mysql_last_push-0.1.4.dist-info/entry_points.txt
my_mcp_project_mysql_last_push-0.1.4.dist-info/METADATA
my_mcp_project_mysql_last_push-0.1.4.dist-info/RECORD
