Metadata-Version: 2.3
Name: my-mcp-project-mysql-last-push
Version: 0.1.4
Summary: Add your description here
Author: 张旭东
Author-email: 张旭东 <zhang_brz@163.com>
Requires-Dist: mcp[cli]>=1.25.0
Requires-Python: >=3.14.2
